ndx_miniscope/__init__.py
ndx_miniscope/spec/ndx-miniscope.extensions.yaml
ndx_miniscope/spec/ndx-miniscope.namespace.yaml
ndx_miniscope/utils/__init__.py
ndx_miniscope/utils/notes.py
ndx_miniscope/utils/nwb.py
ndx_miniscope/utils/settings.py
ndx_miniscope/utils/timestamps.py
ndx_miniscope/utils/video.py
ndx_miniscope-0.5.1.dist-info/LICENSE.txt
ndx_miniscope-0.5.1.dist-info/METADATA
ndx_miniscope-0.5.1.dist-info/WHEEL
ndx_miniscope-0.5.1.dist-info/top_level.txt
ndx_miniscope-0.5.1.dist-info/RECORD
