Metadata-Version: 2.1
Name: ndx-miniscope
Version: 0.5.1
Summary: Represent metadata for Miniscope acquisition system.
Home-page: https://github.com/catalystneuro/ndx-miniscope
Author: Ben Dichter
Author-email: ben.dichter@catalystneuro.com
License: BSD-3
Keywords: NeurodataWithoutBorders,NWB,nwb-extension,ndx-extension
Classifier: Intended Audience :: Developers
Classifier: Intended Audience :: Science/Research
License-File: LICENSE.txt
Requires-Dist: pynwb
Requires-Dist: hdmf-docutils
Requires-Dist: natsort (>=8.3.1)
